azure/mgmt/powerbidedicated/__init__.py
azure/mgmt/powerbidedicated/_configuration.py
azure/mgmt/powerbidedicated/_power_bi_dedicated.py
azure/mgmt/powerbidedicated/_version.py
azure/mgmt/powerbidedicated/aio/__init__.py
azure/mgmt/powerbidedicated/aio/_configuration.py
azure/mgmt/powerbidedicated/aio/_power_bi_dedicated.py
azure/mgmt/powerbidedicated/aio/operations/__init__.py
azure/mgmt/powerbidedicated/aio/operations/_auto_scale_vcores_operations.py
azure/mgmt/powerbidedicated/aio/operations/_capacities_operations.py
azure/mgmt/powerbidedicated/aio/operations/_operations.py
azure/mgmt/powerbidedicated/models/__init__.py
azure/mgmt/powerbidedicated/models/_models.py
azure/mgmt/powerbidedicated/models/_models_py3.py
azure/mgmt/powerbidedicated/models/_power_bi_dedicated_enums.py
azure/mgmt/powerbidedicated/operations/__init__.py
azure/mgmt/powerbidedicated/operations/_auto_scale_vcores_operations.py
azure/mgmt/powerbidedicated/operations/_capacities_operations.py
azure/mgmt/powerbidedicated/operations/_operations.py
azure_mgmt_powerbidedicated-1.0.0.dist-info/METADATA
azure_mgmt_powerbidedicated-1.0.0.dist-info/WHEEL
azure_mgmt_powerbidedicated-1.0.0.dist-info/top_level.txt
azure_mgmt_powerbidedicated-1.0.0.dist-info/RECORD
